{
  "schema": [
    {
      "name": "style",
      "type": 2
    },
    {
      "name": "name",
      "type": 7
    }
  ],
  "rows": [
    {
      "$id": 1,
      "style": 125,
      "name": "미천한 그릇 주제에[XENO:n ]\n끝까지 신에게 거역할 셈인가[XENO:wait wait=key ][XENO:del del=this ]"
    },
    {
      "$id": 2,
      "style": 125,
      "name": "그렇다면 압도적인 힘으로[XENO:n ]\n모든 것을 소멸시켜 주지[XENO:wait wait=key ][XENO:del del=this ]"
    },
    {
      "$id": 3,
      "style": 125,
      "name": "보아라![XENO:n ]\n이게 바로 모든 걸 융합한 세계의 모습이다![XENO:wait wait=key ][XENO:del del=this ]"
    }
  ]
}