{
  "schema": [
    {
      "name": "label",
      "type": 7
    },
    {
      "name": "style",
      "type": 2
    },
    {
      "name": "name",
      "type": 7
    }
  ],
  "rows": [
    {
      "$id": 1,
      "label": "qst201415_0010",
      "style": 82,
      "name": "저기… 슬슬 날이 밝기 시작하는데\n지금 몇 시야?"
    },
    {
      "$id": 2,
      "label": "qst201415_0020",
      "style": 82,
      "name": "아마 7시 정도일걸?\n대결도 슬슬 끝내야겠어"
    },
    {
      "$id": 3,
      "label": "qst201415_0030",
      "style": 82,
      "name": "그렇구나…\n결국 결판이 안 났네"
    },
    {
      "$id": 4,
      "label": "qst201415_0040",
      "style": 82,
      "name": "응…"
    },
    {
      "$id": 5,
      "label": "qst201415_0050",
      "style": 82,
      "name": "하지만 너를 이해할 수 있었어\n자쿠로"
    },
    {
      "$id": 6,
      "label": "qst201415_0060",
      "style": 82,
      "name": "분하지만 인정해 줄게\n너는 확실히 너만의 매력이 있어"
    },
    {
      "$id": 7,
      "label": "qst201415_0070",
      "style": 82,
      "name": "그러는 히카리도 만만치 않아"
    },
    {
      "$id": 8,
      "label": "qst201415_0080",
      "style": 82,
      "name": "역시 내가 유일하게\n라이벌로 인정한 여자야"
    },
    {
      "$id": 9,
      "label": "qst201415_0090",
      "style": 82,
      "name": "[ML:undisp ]"
    },
    {
      "$id": 10,
      "label": "qst201415_0100",
      "style": 82,
      "name": "[ML:undisp ]"
    },
    {
      "$id": 11,
      "label": "qst201415_0110",
      "style": 82,
      "name": "아~ 피곤해\n그래도 재밌었어"
    },
    {
      "$id": 12,
      "label": "qst201415_0120",
      "style": 82,
      "name": "맞아, 이렇게 즐거우니까\n다음에 또 할까?"
    },
    {
      "$id": 13,
      "label": "qst201415_0130",
      "style": 82,
      "name": "좋네\n하자, 하자"
    },
    {
      "$id": 14,
      "label": "qst201415_0140",
      "style": 82,
      "name": "…어흠"
    },
    {
      "$id": 15,
      "label": "qst201415_0150",
      "style": 82,
      "name": "어, 어머\n다들…"
    },
    {
      "$id": 16,
      "label": "qst201415_0160",
      "style": 82,
      "name": "다 같이…\n무슨 일이야?"
    },
    {
      "$id": 17,
      "label": "qst201415_0170",
      "style": 82,
      "name": "아무래도\n그쪽은 결판이 난 거 같지만…"
    },
    {
      "$id": 18,
      "label": "qst201415_0180",
      "style": 82,
      "name": "이쪽은 아직 결판 안 났데이"
    },
    {
      "$id": 19,
      "label": "qst201415_0190",
      "style": 82,
      "name": "아주 제멋대로 굴던데…"
    },
    {
      "$id": 20,
      "label": "qst201415_0200",
      "style": 82,
      "name": "각오는 됐겠지?"
    },
    {
      "$id": 21,
      "label": "qst201415_0210",
      "style": 82,
      "name": "응?\n아니, 그건…"
    },
    {
      "$id": 22,
      "label": "qst201415_0220",
      "style": 82,
      "name": "그러니까 그게"
    },
    {
      "$id": 23,
      "label": "qst201415_0230",
      "style": 82,
      "name": "다들 우리 덕분에\n매력에 대해 고민해 봤잖아?"
    },
    {
      "$id": 24,
      "label": "qst201415_0240",
      "style": 82,
      "name": "그러니 좋은 게 좋은 거로…"
    },
    {
      "$id": 25,
      "label": "qst201415_0250",
      "style": 82,
      "name": "안 될까?"
    },
    {
      "$id": 26,
      "label": "qst201415_0260",
      "style": 82,
      "name": "안 된다"
    },
    {
      "$id": 27,
      "label": "qst201415_0270",
      "style": 82,
      "name": "안 되지"
    },
    {
      "$id": 28,
      "label": "qst201415_0280",
      "style": 82,
      "name": "설교를 해야겠어"
    },
    {
      "$id": 29,
      "label": "qst201415_0290",
      "style": 82,
      "name": "뭐~?"
    },
    {
      "$id": 30,
      "label": "qst201415_0300",
      "style": 82,
      "name": "실컷 날뛰어 놓고…"
    },
    {
      "$id": 31,
      "label": "qst201415_0310",
      "style": 82,
      "name": "죄송합니다…"
    },
    {
      "$id": 32,
      "label": "qst201415_0320",
      "style": 82,
      "name": "주변에 을매나 민폐인지 아나?"
    },
    {
      "$id": 33,
      "label": "qst201415_0330",
      "style": 82,
      "name": "죄송해요…"
    },
    {
      "$id": 34,
      "label": "qst201415_0340",
      "style": 82,
      "name": "반성하고 있니?"
    },
    {
      "$id": 35,
      "label": "qst201415_0350",
      "style": 82,
      "name": "반성하고 있습니다"
    },
    {
      "$id": 36,
      "label": "qst201415_0360",
      "style": 82,
      "name": "정말인가?"
    },
    {
      "$id": 37,
      "label": "qst201415_0370",
      "style": 82,
      "name": "정말이에요"
    },
    {
      "$id": 38,
      "label": "qst201415_0380",
      "style": 82,
      "name": "그럼 둘이 한 대결에 결판이 안 난 모양이니"
    },
    {
      "$id": 39,
      "label": "qst201415_0390",
      "style": 82,
      "name": "벌칙 게임은 둘이서 받도록 할까?"
    },
    {
      "$id": 40,
      "label": "qst201415_0400",
      "style": 82,
      "name": "그래, 그기 좋겠구마"
    },
    {
      "$id": 41,
      "label": "qst201415_0410",
      "style": 82,
      "name": "[ML:undisp ]"
    },
    {
      "$id": 42,
      "label": "qst201415_0420",
      "style": 82,
      "name": "잠깐만"
    },
    {
      "$id": 43,
      "label": "qst201415_0430",
      "style": 82,
      "name": "무슨 문제라도?"
    },
    {
      "$id": 44,
      "label": "qst201415_0440",
      "style": 82,
      "name": "…없습니다"
    },
    {
      "$id": 45,
      "label": "qst201415_0450",
      "style": 82,
      "name": "…내가 왜 이런 수모를 겪어야 해?"
    },
    {
      "$id": 46,
      "label": "qst201415_0460",
      "style": 82,
      "name": "투덜거리지 마\n제대로 안 추면 더 무서운 일이 있을걸?"
    },
    {
      "$id": 47,
      "label": "qst201415_0470",
      "style": 82,
      "name": "진짜 최악이야"
    }
  ]
}