{
  "schema": [
    {
      "name": "label",
      "type": 7
    },
    {
      "name": "style",
      "type": 2
    },
    {
      "name": "name",
      "type": 7
    }
  ],
  "rows": [
    {
      "$id": 1,
      "label": "tlk42100181_01_msg0001",
      "style": 84,
      "name": "마고마고의 할아버지는\n정~말 바빠모"
    },
    {
      "$id": 2,
      "label": "tlk42100181_01_msg0002",
      "style": 84,
      "name": "다른 곳에서는 많은 사람이\n상품을 가지고 오는데\n여기는 아니라서 힘들어모"
    },
    {
      "$id": 3,
      "label": "tlk42100181_01_msg0003",
      "style": 84,
      "name": "높은 사람이 허락을 안 하면\n상품을 못 갖고 와모\n왜? 왜 그런 거야모?"
    },
    {
      "$id": 4,
      "label": "tlk42100181_01_msg0004",
      "style": 84,
      "name": "빨리 밤이 돼라모~!\n할아버지의 일 끝나라모~!"
    }
  ]
}