{
  "schema": [
    {
      "name": "label",
      "type": 7
    },
    {
      "name": "style",
      "type": 2
    },
    {
      "name": "name",
      "type": 7
    }
  ],
  "rows": [
    {
      "$id": 1,
      "label": "tlk43420341_05_msg0001",
      "style": 84,
      "name": "폰스 마임에 있는\n콜 씨라는 사람 알지?"
    },
    {
      "$id": 2,
      "label": "tlk43420341_05_msg0002",
      "style": 84,
      "name": "예전에 반담이\n소개해 준 적이 있었어"
    },
    {
      "$id": 3,
      "label": "tlk43420341_05_msg0003",
      "style": 84,
      "name": "얼마 전 폰스 마임에 간 김에\n잠깐 들렀지"
    },
    {
      "$id": 4,
      "label": "tlk43420341_05_msg0004",
      "style": 84,
      "name": "건강이 점점 안 좋아지는지\n괴로워 보였어"
    },
    {
      "$id": 5,
      "label": "tlk43420341_05_msg0005",
      "style": 84,
      "name": "도울 방법이 있으면 좋을 텐데…"
    }
  ]
}