{
  "schema": [
    {
      "name": "style",
      "type": 2
    },
    {
      "name": "name",
      "type": 7
    }
  ],
  "rows": [
    {
      "$id": 1,
      "style": 124,
      "name": ""
    },
    {
      "$id": 2,
      "style": 124,
      "name": "기다리고 있었습니다모"
    },
    {
      "$id": 3,
      "style": 124,
      "name": ""
    },
    {
      "$id": 4,
      "style": 124,
      "name": "용사"
    },
    {
      "$id": 5,
      "style": 124,
      "name": "리키를 부르거라모!"
    },
    {
      "$id": 6,
      "style": 124,
      "name": ""
    },
    {
      "$id": 7,
      "style": 124,
      "name": "자, 가라모! 용사!"
    },
    {
      "$id": 8,
      "style": 124,
      "name": ""
    },
    {
      "$id": 9,
      "style": 124,
      "name": ""
    },
    {
      "$id": 10,
      "style": 124,
      "name": ""
    },
    {
      "$id": 11,
      "style": 124,
      "name": ""
    },
    {
      "$id": 12,
      "style": 124,
      "name": ""
    },
    {
      "$id": 13,
      "style": 124,
      "name": ""
    },
    {
      "$id": 14,
      "style": 124,
      "name": "이놈이"
    },
    {
      "$id": 15,
      "style": 124,
      "name": ""
    },
    {
      "$id": 16,
      "style": 124,
      "name": "용사야모!"
    },
    {
      "$id": 17,
      "style": 124,
      "name": ""
    },
    {
      "$id": 18,
      "style": 124,
      "name": "용사, 빚 갚아모!"
    },
    {
      "$id": 19,
      "style": 124,
      "name": "용사, 외상 갚아모!"
    },
    {
      "$id": 20,
      "style": 124,
      "name": "용사, 빨리 갔다 와모!"
    },
    {
      "$id": 21,
      "style": 124,
      "name": "용사, 꾸물거리면 안 돼모!"
    },
    {
      "$id": 22,
      "style": 124,
      "name": "용사, 기대에 부응해모!"
    },
    {
      "$id": 23,
      "style": 124,
      "name": ""
    },
    {
      "$id": 24,
      "style": 124,
      "name": "정숙!!"
    },
    {
      "$id": 25,
      "style": 124,
      "name": ""
    },
    {
      "$id": 26,
      "style": 124,
      "name": "소개하겠습니다모"
    },
    {
      "$id": 27,
      "style": 124,
      "name": ""
    },
    {
      "$id": 28,
      "style": 124,
      "name": "올해의 전설의 용사"
    },
    {
      "$id": 29,
      "style": 124,
      "name": ""
    },
    {
      "$id": 30,
      "style": 124,
      "name": "리키입니다모"
    },
    {
      "$id": 31,
      "style": 124,
      "name": ""
    },
    {
      "$id": 32,
      "style": 124,
      "name": "안녕"
    },
    {
      "$id": 33,
      "style": 124,
      "name": "친구들!"
    },
    {
      "$id": 34,
      "style": 124,
      "name": ""
    },
    {
      "$id": 35,
      "style": 124,
      "name": "올해의 전설의 용사로\n뽑힌 리키야모"
    },
    {
      "$id": 36,
      "style": 124,
      "name": ""
    },
    {
      "$id": 37,
      "style": 124,
      "name": "잘 부탁해모~!"
    },
    {
      "$id": 38,
      "style": 124,
      "name": ""
    }
  ]
}