{
  "schema": [
    {
      "name": "style",
      "type": 2
    },
    {
      "name": "name",
      "type": 7
    }
  ],
  "rows": [
    {
      "$id": 1,
      "style": 124,
      "name": ""
    },
    {
      "$id": 2,
      "style": 124,
      "name": "메이너스 님…"
    },
    {
      "$id": 3,
      "style": 124,
      "name": ""
    },
    {
      "$id": 4,
      "style": 124,
      "name": "얼마 남지 않았습니다"
    },
    {
      "$id": 5,
      "style": 124,
      "name": ""
    },
    {
      "$id": 6,
      "style": 124,
      "name": "누구도 두려워하지 않으며"
    },
    {
      "$id": 7,
      "style": 124,
      "name": ""
    },
    {
      "$id": 8,
      "style": 124,
      "name": "내려 주신 생을 향유할 수 있는 세계"
    },
    {
      "$id": 9,
      "style": 124,
      "name": ""
    },
    {
      "$id": 10,
      "style": 124,
      "name": "우리의 비원은"
    },
    {
      "$id": 11,
      "style": 124,
      "name": ""
    },
    {
      "$id": 12,
      "style": 124,
      "name": "바로 눈앞까지 와 있습니다"
    },
    {
      "$id": 13,
      "style": 124,
      "name": ""
    },
    {
      "$id": 14,
      "style": 124,
      "name": "그래…"
    },
    {
      "$id": 15,
      "style": 124,
      "name": ""
    },
    {
      "$id": 16,
      "style": 124,
      "name": "그 전에 모나드를"
    },
    {
      "$id": 17,
      "style": 124,
      "name": ""
    },
    {
      "$id": 18,
      "style": 124,
      "name": "더 늦기 전에"
    },
    {
      "$id": 19,
      "style": 124,
      "name": ""
    },
    {
      "$id": 20,
      "style": 124,
      "name": "모나드를 부술 수만 있다면"
    },
    {
      "$id": 21,
      "style": 124,
      "name": ""
    },
    {
      "$id": 22,
      "style": 124,
      "name": "분명 이길 수 있다"
    },
    {
      "$id": 23,
      "style": 124,
      "name": ""
    },
    {
      "$id": 24,
      "style": 124,
      "name": "아직 존재하고 있다"
    },
    {
      "$id": 25,
      "style": 124,
      "name": ""
    },
    {
      "$id": 26,
      "style": 124,
      "name": "나는 느낄 수 있다"
    },
    {
      "$id": 27,
      "style": 124,
      "name": ""
    },
    {
      "$id": 28,
      "style": 124,
      "name": "잔자여"
    },
    {
      "$id": 29,
      "style": 124,
      "name": ""
    },
    {
      "$id": 30,
      "style": 124,
      "name": "이번에야말로…"
    },
    {
      "$id": 31,
      "style": 124,
      "name": ""
    },
    {
      "$id": 32,
      "style": 124,
      "name": "두 번 다시…"
    },
    {
      "$id": 33,
      "style": 124,
      "name": ""
    }
  ]
}