{
  "schema" : [ {
    "name" : "label",
    "type" : 9
  }, {
    "name" : "style",
    "type" : 2
  }, {
    "name" : "name",
    "type" : 7
  } ],
  "rows" : [ {
    "$id" : 1,
    "label" : "ev11085100_0010",
    "style" : 124,
    "name" : "[ML:undisp ]……"
  }, {
    "$id" : 2,
    "label" : "ev11085100_0020",
    "style" : 124,
    "name" : "[ML:undisp ]……"
  }, {
    "$id" : 3,
    "label" : "ev11085100_0030",
    "style" : 124,
    "name" : "상처를 보니 뫼비우스는 아닌 거 같아"
  }, {
    "$id" : 4,
    "label" : "ev11085100_0040",
    "style" : 124,
    "name" : "떠돌아다니던 중에\n몬스터에게 습격당했을 거야"
  }, {
    "$id" : 5,
    "label" : "ev11085100_0050",
    "style" : 124,
    "name" : "미안, 이건 내 잘못이야"
  }, {
    "$id" : 6,
    "label" : "ev11085100_0060",
    "style" : 124,
    "name" : "널 깨워서 출발했어야 했는데"
  }, {
    "$id" : 7,
    "label" : "ev11085100_0065",
    "style" : 124,
    "name" : "[ML:undisp ]놀라는 애드리브"
  }, {
    "$id" : 8,
    "label" : "ev11085100_0070",
    "style" : 124,
    "name" : "너는 잘못한 거 없어"
  }, {
    "$id" : 9,
    "label" : "ev11085100_0080",
    "style" : 124,
    "name" : "느긋하게 잠이나 잔 내 잘못이지"
  }, {
    "$id" : 10,
    "label" : "ev11085100_0090",
    "style" : 124,
    "name" : "겨우 찾았는데……"
  }, {
    "$id" : 11,
    "label" : "ev11085100_0100",
    "style" : 124,
    "name" : "미안하다……"
  } ]
}