{
  "schema": [
    {
      "name": "label",
      "type": 7
    },
    {
      "name": "style",
      "type": 2
    },
    {
      "name": "name",
      "type": 7
    }
  ],
  "rows": [
    {
      "$id": 1,
      "label": "tlk70000073_05_msg0001",
      "style": 84,
      "name": "너희, 정말 일을 잘했던데?"
    },
    {
      "$id": 2,
      "label": "tlk70000073_05_msg0002",
      "style": 84,
      "name": "이런 비상사태에도 왕도 녀석들은\n단단히 결속해서 사기를 높이고 있어"
    },
    {
      "$id": 3,
      "label": "tlk70000073_05_msg0003",
      "style": 84,
      "name": "덕분에 저항군 캠프 녀석들이\n어떻게 지내고 있는지 궁금해졌어"
    },
    {
      "$id": 4,
      "label": "tlk70000073_05_msg0004",
      "style": 84,
      "name": "그때는 나름대로 즐거웠어\n이제 말할 수 없는 게 아쉽지만"
    },
    {
      "$id": 5,
      "label": "tlk70000073_05_msg0005",
      "style": 84,
      "name": "『소중한 건 잃은 뒤에 깨닫는다』고 했나?\n그게 사실이구나 싶어서 짜증 나"
    },
    {
      "$id": 6,
      "label": "tlk70000073_05_msg0006",
      "style": 84,
      "name": "아~ 좀 더 똑똑하게 살려고 했는데…"
    },
    {
      "$id": 7,
      "label": "tlk70000073_05_msg0007",
      "style": 84,
      "name": "……"
    },
    {
      "$id": 8,
      "label": "tlk70000073_05_msg0008",
      "style": 84,
      "name": "있잖아, 너는 인생에서 언제까지\n만회할 기회가 주어진다고 생각해?\n나도 아직… 늦지 않았을까?"
    }
  ]
}