{
  "schema": [
    {
      "name": "label",
      "type": 7
    },
    {
      "name": "style",
      "type": 2
    },
    {
      "name": "name",
      "type": 7
    }
  ],
  "rows": [
    {
      "$id": 1,
      "label": "tlk70000034_01_msg0001",
      "style": 84,
      "name": "안녕! 너희는 소중한 사람과\n신뢰를 잘 쌓고 있니?"
    },
    {
      "$id": 2,
      "label": "tlk70000034_01_msg0002",
      "style": 84,
      "name": "예를 들어 블레이드와 드라이버는\n함께 싸우고 의뢰 해결을 반복해 나가면서\n점점 마음을 주고받을 수 있게 되겠지"
    },
    {
      "$id": 3,
      "label": "tlk70000034_01_msg0003",
      "style": 84,
      "name": "천 마디 말보다 한 번의 행동이\n마음을 더 잘 표현할 때도\n있다는 거야"
    },
    {
      "$id": 4,
      "label": "tlk70000034_01_msg0004",
      "style": 84,
      "name": "하지만 사랑하는 이의 신뢰를 얻으려면?\n사랑을 믿지 않는 그녀를 위해\n나는 대체 뭘 해야 하지?"
    },
    {
      "$id": 5,
      "label": "tlk70000034_01_msg0005",
      "style": 84,
      "name": "아아, 가슴을 쥐어뜯고 싶은\n이 달콤한 고통! 이게 바로… 사랑!"
    }
  ]
}