{
  "schema": [
    {
      "name": "label",
      "type": 7
    },
    {
      "name": "style",
      "type": 2
    },
    {
      "name": "name",
      "type": 7
    }
  ],
  "rows": [
    {
      "$id": 1,
      "label": "tlk70000017_04_msg0001",
      "style": 84,
      "name": "그 아케디아라는 나라는\n아무래도 신용이 가지 않아"
    },
    {
      "$id": 2,
      "label": "tlk70000017_04_msg0002",
      "style": 84,
      "name": "아르스트 내의 여러 나라에\n엄청난 영향력을 행사한다는\n소문은 있지만…"
    },
    {
      "$id": 3,
      "label": "tlk70000017_04_msg0003",
      "style": 84,
      "name": "교의니 신탁이니 하는\n불확실한 것을 내세우는 녀석들은\n도저히 좋아할 수가 없어"
    },
    {
      "$id": 4,
      "label": "tlk70000017_04_msg0004",
      "style": 84,
      "name": "나도 나름 과학자 나부랭이라서 말이네…\n그런 애매한 것은 무심코 의심부터 하게 되지"
    },
    {
      "$id": 5,
      "label": "tlk70000017_04_msg0005",
      "style": 84,
      "name": "거리에도 신자가 많이 있고\n큰 잘못을 저지르진 않았으니\n대놓고 말은 못 하지만 말이야"
    }
  ]
}