{
  "schema" : [ {
    "name" : "label",
    "type" : 9
  }, {
    "name" : "style",
    "type" : 2
  }, {
    "name" : "name",
    "type" : 7
  } ],
  "rows" : [ {
    "$id" : 1,
    "label" : "ev05240100_0010",
    "style" : 124,
    "name" : "세나…… 맞지?"
  }, {
    "$id" : 2,
    "label" : "ev05240100_0020",
    "style" : 124,
    "name" : "뭐? 아…… 음, 넌……"
  }, {
    "$id" : 3,
    "label" : "ev05240100_0030",
    "style" : 124,
    "name" : "나는 3기인 미오야"
  }, {
    "$id" : 4,
    "label" : "ev05240100_0040",
    "style" : 124,
    "name" : "일단 이렇게 만난 건 처음이지?"
  }, {
    "$id" : 5,
    "label" : "ev05240100_0050",
    "style" : 124,
    "name" : "미, 미안해\n이름도 금방 기억 못 해서……"
  }, {
    "$id" : 6,
    "label" : "ev05240100_0060",
    "style" : 124,
    "name" : "내, 내 생각에도……\n처, 처음인 거 같아"
  }, {
    "$id" : 7,
    "label" : "ev05240100_0070",
    "style" : 124,
    "name" : "어, 음……"
  }, {
    "$id" : 8,
    "label" : "ev05240100_0080",
    "style" : 124,
    "name" : "지금 모의전 파트너를 찾고 있는데"
  }, {
    "$id" : 9,
    "label" : "ev05240100_0090",
    "style" : 124,
    "name" : "모의전 파트너?"
  }, {
    "$id" : 10,
    "label" : "ev05240100_0100",
    "style" : 124,
    "name" : "속도에는 꽤 자신 있는 편인데……"
  }, {
    "$id" : 11,
    "label" : "ev05240100_0105",
    "style" : 124,
    "name" : "힘이 영 아니거든"
  }, {
    "$id" : 12,
    "label" : "ev05240100_0110",
    "style" : 124,
    "name" : "분대장님께서 널 추천해 주셨어"
  }, {
    "$id" : 13,
    "label" : "ev05240100_0115",
    "style" : 124,
    "name" : "힘이 엄청 세다던데"
  }, {
    "$id" : 14,
    "label" : "ev05240100_0120",
    "style" : 124,
    "name" : "아, 아니야\n평범한 수준이지…… 평범……"
  }, {
    "$id" : 15,
    "label" : "ev05240100_0130",
    "style" : 124,
    "name" : "어때? 같이 할래?"
  }, {
    "$id" : 16,
    "label" : "ev05240100_0140",
    "style" : 124,
    "name" : "같이 하자고?"
  }, {
    "$id" : 17,
    "label" : "ev05240100_0150",
    "style" : 124,
    "name" : "나라도…… 괜찮겠어?"
  }, {
    "$id" : 18,
    "label" : "ev05240100_0160",
    "style" : 124,
    "name" : "부탁은 내가 했는데?"
  }, {
    "$id" : 19,
    "label" : "ev05240100_0165",
    "style" : 124,
    "name" : "선택은 네 몫이야"
  }, {
    "$id" : 20,
    "label" : "ev05240100_0170",
    "style" : 124,
    "name" : "나, 나라도 괜찮다면……"
  }, {
    "$id" : 21,
    "label" : "ev05240100_0175",
    "style" : 124,
    "name" : "잘 부탁할게……!"
  }, {
    "$id" : 22,
    "label" : "ev05240100_0180",
    "style" : 124,
    "name" : "정말? 와~!"
  }, {
    "$id" : 23,
    "label" : "ev05240100_0190",
    "style" : 124,
    "name" : "그럼 이제 한 팀이네"
  }, {
    "$id" : 24,
    "label" : "ev05240100_0200",
    "style" : 124,
    "name" : "응……! 고마워!"
  } ]
}